iGetMusic/__init__.py
iGetMusic/iGet.py
iGetMusic-0.1.0.dist-info/LICENCE
iGetMusic-0.1.0.dist-info/METADATA
iGetMusic-0.1.0.dist-info/WHEEL
iGetMusic-0.1.0.dist-info/top_level.txt
iGetMusic-0.1.0.dist-info/RECORD
